{"stats":{"minecraft:custom":{"minecraft:time_since_rest":831038,"minecraft:sprint_one_cm":3763332,"minecraft:walk_one_cm":1369617,"minecraft:interact_with_anvil":18,"minecraft:mob_kills":2,"minecraft:drop":7,"minecraft:damage_dealt":225,"minecraft:fly_one_cm":12077621,"minecraft:open_chest":107,"minecraft:crouch_one_cm":33412,"minecraft:play_time":4238997,"minecraft:deaths":3,"minecraft:sneak_time":21761,"minecraft:interact_with_lectern":42,"minecraft:jump":42078,"minecraft:leave_game":79,"minecraft:time_since_death":831013,"minecraft:climb_one_cm":2298,"minecraft:total_world_time":5867307},"minecraft:dropped":{"minecraft:iron_ingot":1,"minecraft:writable_book":4,"minecraft:camel_spawn_egg":1,"minecraft:redstone_block":1},"minecraft:picked_up":{"minecraft:stick":1,"minecraft:light_blue_concrete":7,"minecraft:redstone_block":20,"minecraft:ladder":5,"minecraft:anvil":9,"minecraft:porkchop":4,"minecraft:oak_log":16,"minecraft:stone_button":3,"minecraft:oak_sign":1,"minecraft:wheat_seeds":9,"minecraft:writable_book":15,"minecraft:iron_ingot":1,"minecraft:dark_oak_sign":2,"minecraft:white_concrete":1,"minecraft:written_book":2,"minecraft:oak_button":2,"minecraft:oak_sapling":1,"minecraft:cobblestone":15},"minecraft:killed":{"minecraft:pig":2},"minecraft:used":{"minecraft:glass":28,"minecraft:cherry_sapling":4,"minecraft:water_bucket":1,"minecraft:lever":2,"minecraft:writable_book":791,"minecraft:lava_bucket":1,"minecraft:armor_stand":35,"minecraft:stone_button":14,"minecraft:command_block":52,"minecraft:orange_concrete":1,"minecraft:ladder":58,"minecraft:red_concrete":1,"minecraft:light_gray_concrete":56,"minecraft:barrier":6,"minecraft:red_stained_glass":8,"minecraft:grass_block":28,"minecraft:dark_oak_sign":9,"minecraft:redstone":4,"minecraft:oak_button":7,"minecraft:pig_spawn_egg":1,"minecraft:oak_sign":20,"minecraft:lectern":3,"minecraft:chest":22,"minecraft:stone":79,"minecraft:cherry_leaves":1,"minecraft:redstone_block":34,"minecraft:white_dye":3,"minecraft:glow_ink_sac":3,"minecraft:spruce_sapling":1,"minecraft:grass":1,"minecraft:structure_block":4,"minecraft:pink_petals":85,"minecraft:torch":12,"minecraft:repeater":5,"minecraft:diamond_sword":3,"minecraft:redstone_lamp":3,"minecraft:anvil":3,"minecraft:lime_concrete":11,"minecraft:written_book":36,"minecraft:green_dye":1,"minecraft:light_blue_concrete":593,"minecraft:iron_trapdoor":11,"minecraft:hopper":3,"minecraft:oak_sapling":2,"minecraft:yellow_concrete":2,"minecraft:camel_spawn_egg":1,"minecraft:gray_concrete":110,"minecraft:white_concrete":603,"minecraft:red_dye":1,"minecraft:bone_meal":38}},"DataVersion":3578}